prof/__init__.py
prof/main.py
prof/prof.py
prof_qu-2.dist-info/METADATA
prof_qu-2.dist-info/WHEEL
prof_qu-2.dist-info/entry_points.txt
prof_qu-2.dist-info/top_level.txt
prof_qu-2.dist-info/RECORD
